nendo_plugin_transcribe_whisper/__init__.py
nendo_plugin_transcribe_whisper/config.py
nendo_plugin_transcribe_whisper/plugin.py
nendo_plugin_transcribe_whisper-0.1.0.dist-info/LICENSE
nendo_plugin_transcribe_whisper-0.1.0.dist-info/METADATA
nendo_plugin_transcribe_whisper-0.1.0.dist-info/WHEEL
nendo_plugin_transcribe_whisper-0.1.0.dist-info/RECORD
