Metadata-Version: 2.1
Name: nendo-plugin-transcribe-whisper
Version: 0.1.0
Summary: A nendo plugin for speech transcription, based on Whisper by OpenAI.
Home-page: https://okio.ai
License: MIT
Keywords: AI,generative,music,okio,nendo,audio production,audio transcription,music analysis,song analysis
Author: Aaron Abebe
Author-email: aaron@okio.ai
Requires-Python: >=3.8,<3.11
Classifier: Development Status :: 5 - Production/Stable
Classifier: Intended Audience :: Developers
Classifier: License :: OSI Approved :: MIT License
Classifier: Operating System :: OS Independent
Classifier: Programming Language :: Python :: 3
Classifier: Programming Language :: Python :: 3.8
Classifier: Programming Language :: Python :: 3.9
Classifier: Programming Language :: Python :: 3.10
Classifier: Topic :: Multimedia :: Sound/Audio
Requires-Dist: accelerate (>=0.24.1,<0.25.0)
Requires-Dist: nendo (>=0.2.0,<0.3.0)
Requires-Dist: pydantic (>=2.4.2,<3.0.0)
Requires-Dist: transformers (>=4.37.2,<5.0.0)
Project-URL: Repository, https://github.com/okio-ai/nendo_plugin_transcribe_whisper
